{".class": "MypyFile", "_fullname": "memory_size", "is_partial_stub_package": false, "is_stub": false, "names": {".class": "SymbolTable", "__doc__": {".class": "SymbolTableNode", "kind": "Gdef", "node": {".class": "Var", "flags": ["is_ready"], "fullname": "memory_size.__doc__", "name": "__doc__", "type": "builtins.str"}}, "__file__": {".class": "SymbolTableNode", "kind": "Gdef", "node": {".class": "Var", "flags": ["is_ready"], "fullname": "memory_size.__file__", "name": "__file__", "type": "builtins.str"}}, "__name__": {".class": "SymbolTableNode", "kind": "Gdef", "node": {".class": "Var", "flags": ["is_ready"], "fullname": "memory_size.__name__", "name": "__name__", "type": "builtins.str"}}, "__package__": {".class": "SymbolTableNode", "kind": "Gdef", "node": {".class": "Var", "flags": ["is_ready"], "fullname": "memory_size.__package__", "name": "__package__", "type": "builtins.str"}}, "load": {".class": "SymbolTableNode", "kind": "Gdef", "node": {".class": "FuncDef", "arg_kinds": [0], "arg_names": ["num_bits"], "flags": [], "fullname": "memory_size.load", "name": "load", "type": null}}, "memory_len": {".class": "SymbolTableNode", "kind": "Gdef", "node": {".class": "Var", "flags": ["is_suppressed_import", "is_ready"], "fullname": "memory_size.memory_len", "name": "memory_len", "type": {".class": "AnyType", "missing_import_name": "memory_size.memory_len", "source_any": null, "type_of_any": 3}}}, "sweep": {".class": "SymbolTableNode", "kind": "Gdef", "node": {".class": "Var", "flags": ["is_suppressed_import", "is_ready"], "fullname": "memory_size.sweep", "name": "sweep", "type": {".class": "AnyType", "missing_import_name": "memory_size.sweep", "source_any": null, "type_of_any": 3}}}}, "path": "/home/bew/archive/typed_project/(deepmind)bsuite/bsuite/experiments/memory_size/memory_size.py"}