{".class": "MypyFile", "_fullname": "sanic_example", "is_partial_stub_package": false, "is_stub": false, "names": {".class": "SymbolTable", "Cache": {".class": "SymbolTableNode", "kind": "Gdef", "node": {".class": "Var", "flags": ["is_suppressed_import", "is_ready"], "fullname": "sanic_example.Cache", "name": "Cache", "type": {".class": "AnyType", "missing_import_name": "sanic_example.Cache", "source_any": null, "type_of_any": 3}}}, "JsonSerializer": {".class": "SymbolTableNode", "kind": "Gdef", "node": {".class": "Var", "flags": ["is_suppressed_import", "is_ready"], "fullname": "sanic_example.JsonSerializer", "name": "JsonSerializer", "type": {".class": "AnyType", "missing_import_name": "sanic_example.JsonSerializer", "source_any": null, "type_of_any": 3}}}, "Sanic": {".class": "SymbolTableNode", "kind": "Gdef", "node": {".class": "Var", "flags": ["is_suppressed_import", "is_ready"], "fullname": "sanic_example.Sanic", "name": "Sanic", "type": {".class": "AnyType", "missing_import_name": "sanic_example.Sanic", "source_any": null, "type_of_any": 3}}}, "__doc__": {".class": "SymbolTableNode", "kind": "Gdef", "node": {".class": "Var", "flags": ["is_ready"], "fullname": "sanic_example.__doc__", "name": "__doc__", "type": "builtins.str"}}, "__file__": {".class": "SymbolTableNode", "kind": "Gdef", "node": {".class": "Var", "flags": ["is_ready"], "fullname": "sanic_example.__file__", "name": "__file__", "type": "builtins.str"}}, "__name__": {".class": "SymbolTableNode", "kind": "Gdef", "node": {".class": "Var", "flags": ["is_ready"], "fullname": "sanic_example.__name__", "name": "__name__", "type": "builtins.str"}}, "__package__": {".class": "SymbolTableNode", "kind": "Gdef", "node": {".class": "Var", "flags": ["is_ready"], "fullname": "sanic_example.__package__", "name": "__package__", "type": "builtins.str"}}, "app": {".class": "SymbolTableNode", "kind": "Gdef", "node": {".class": "Var", "flags": [], "fullname": "sanic_example.app", "name": "app", "type": {".class": "AnyType", "missing_import_name": "sanic_example.Sanic", "source_any": {".class": "AnyType", "missing_import_name": "sanic_example.Sanic", "source_any": null, "type_of_any": 3}, "type_of_any": 7}}}, "asyncio": {".class": "SymbolTableNode", "cross_ref": "asyncio", "kind": "Gdef"}, "cached": {".class": "SymbolTableNode", "kind": "Gdef", "node": {".class": "Var", "flags": ["is_suppressed_import", "is_ready"], "fullname": "sanic_example.cached", "name": "cached", "type": {".class": "AnyType", "missing_import_name": "sanic_example.cached", "source_any": null, "type_of_any": 3}}}, "expensive_call": {".class": "SymbolTableNode", "kind": "Gdef", "node": {".class": "Decorator", "func": {".class": "FuncDef", "arg_kinds": [], "arg_names": [], "flags": ["is_coroutine", "is_decorated"], "fullname": "sanic_example.expensive_call", "name": "expensive_call", "type": null}, "is_overload": false, "var": {".class": "Var", "flags": ["is_ready"], "fullname": null, "name": "expensive_call", "type": {".class": "AnyType", "missing_import_name": "sanic_example.cached", "source_any": {".class": "AnyType", "missing_import_name": "sanic_example.cached", "source_any": null, "type_of_any": 3}, "type_of_any": 7}}}}, "json": {".class": "SymbolTableNode", "kind": "Gdef", "node": {".class": "Var", "flags": ["is_suppressed_import", "is_ready"], "fullname": "sanic_example.json", "name": "json", "type": {".class": "AnyType", "missing_import_name": "sanic_example.json", "source_any": null, "type_of_any": 3}}}, "log": {".class": "SymbolTableNode", "kind": "Gdef", "node": {".class": "Var", "flags": ["is_suppressed_import", "is_ready"], "fullname": "sanic_example.log", "name": "log", "type": {".class": "AnyType", "missing_import_name": "sanic_example.log", "source_any": null, "type_of_any": 3}}}, "main": {".class": "SymbolTableNode", "kind": "Gdef", "node": {".class": "Decorator", "func": {".class": "FuncDef", "arg_kinds": [0], "arg_names": ["request"], "flags": ["is_coroutine", "is_decorated"], "fullname": "sanic_example.main", "name": "main", "type": null}, "is_overload": false, "var": {".class": "Var", "flags": ["is_ready"], "fullname": null, "name": "main", "type": {".class": "AnyType", "missing_import_name": "sanic_example.Sanic", "source_any": {".class": "AnyType", "missing_import_name": "sanic_example.Sanic", "source_any": null, "type_of_any": 3}, "type_of_any": 7}}}}, "reuse": {".class": "SymbolTableNode", "kind": "Gdef", "node": {".class": "Decorator", "func": {".class": "FuncDef", "arg_kinds": [0], "arg_names": ["request"], "flags": ["is_coroutine", "is_decorated"], "fullname": "sanic_example.reuse", "name": "reuse", "type": null}, "is_overload": false, "var": {".class": "Var", "flags": ["is_ready"], "fullname": null, "name": "reuse", "type": {".class": "AnyType", "missing_import_name": "sanic_example.Sanic", "source_any": {".class": "AnyType", "missing_import_name": "sanic_example.Sanic", "source_any": null, "type_of_any": 3}, "type_of_any": 7}}}}, "reuse_data": {".class": "SymbolTableNode", "kind": "Gdef", "node": {".class": "FuncDef", "arg_kinds": [], "arg_names": [], "flags": ["is_coroutine"], "fullname": "sanic_example.reuse_data", "name": "reuse_data", "type": null}}}, "path": "/home/bew/archive/typed_project/(argaen)aiocache/examples/frameworks/sanic_example.py"}