{".class": "MypyFile", "_fullname": "server", "is_partial_stub_package": false, "is_stub": false, "names": {".class": "SymbolTable", "AIOCACHE_BACKENDS": {".class": "SymbolTableNode", "kind": "Gdef", "node": {".class": "Var", "flags": [], "fullname": "server.AIOCACHE_BACKENDS", "name": "AIOCACHE_BACKENDS", "type": {".class": "Instance", "args": ["builtins.str", {".class": "AnyType", "missing_import_name": "server.Cache", "source_any": {".class": "AnyType", "missing_import_name": "server.Cache", "source_any": null, "type_of_any": 3}, "type_of_any": 7}], "type_ref": "builtins.dict"}}}, "Cache": {".class": "SymbolTableNode", "kind": "Gdef", "node": {".class": "Var", "flags": ["is_suppressed_import", "is_ready"], "fullname": "server.Cache", "name": "Cache", "type": {".class": "AnyType", "missing_import_name": "server.Cache", "source_any": null, "type_of_any": 3}}}, "CacheManager": {".class": "SymbolTableNode", "kind": "Gdef", "node": {".class": "TypeInfo", "_promote": null, "abstract_attributes": [], "bases": ["builtins.object"], "declared_metaclass": null, "defn": {".class": "ClassDef", "fullname": "server.CacheManager", "name": "CacheManager", "type_vars": []}, "flags": [], "fullname": "server.CacheManager", "metaclass_type": null, "metadata": {}, "module_name": "server", "mro": ["server.CacheManager", "builtins.object"], "names": {".class": "SymbolTable", "__init__": {".class": "SymbolTableNode", "kind": "Mdef", "node": {".class": "FuncDef", "arg_kinds": [0, 0], "arg_names": ["self", "backend"], "flags": [], "fullname": "server.CacheManager.__init__", "name": "__init__", "type": null}}, "cache": {".class": "SymbolTableNode", "implicit": true, "kind": "Mdef", "node": {".class": "Var", "flags": [], "fullname": "server.CacheManager.cache", "name": "cache", "type": {".class": "AnyType", "missing_import_name": null, "source_any": null, "type_of_any": 1}}}, "get": {".class": "SymbolTableNode", "kind": "Mdef", "node": {".class": "FuncDef", "arg_kinds": [0, 0], "arg_names": ["self", "key"], "flags": ["is_coroutine"], "fullname": "server.CacheManager.get", "name": "get", "type": null}}, "set": {".class": "SymbolTableNode", "kind": "Mdef", "node": {".class": "FuncDef", "arg_kinds": [0, 0, 0], "arg_names": ["self", "key", "value"], "flags": ["is_coroutine"], "fullname": "server.CacheManager.set", "name": "set", "type": null}}}, "tuple_type": null, "type_vars": [], "typeddict_type": null}}, "__doc__": {".class": "SymbolTableNode", "kind": "Gdef", "node": {".class": "Var", "flags": ["is_ready"], "fullname": "server.__doc__", "name": "__doc__", "type": "builtins.str"}}, "__file__": {".class": "SymbolTableNode", "kind": "Gdef", "node": {".class": "Var", "flags": ["is_ready"], "fullname": "server.__file__", "name": "__file__", "type": "builtins.str"}}, "__name__": {".class": "SymbolTableNode", "kind": "Gdef", "node": {".class": "Var", "flags": ["is_ready"], "fullname": "server.__name__", "name": "__name__", "type": "builtins.str"}}, "__package__": {".class": "SymbolTableNode", "kind": "Gdef", "node": {".class": "Var", "flags": ["is_ready"], "fullname": "server.__package__", "name": "__package__", "type": "builtins.str"}}, "argparse": {".class": "SymbolTableNode", "cross_ref": "argparse", "kind": "Gdef"}, "args": {".class": "SymbolTableNode", "kind": "Gdef", "node": {".class": "Var", "flags": [], "fullname": "server.args", "name": "args", "type": "argparse.Namespace"}}, "asyncio": {".class": "SymbolTableNode", "cross_ref": "asyncio", "kind": "Gdef"}, "handler_get": {".class": "SymbolTableNode", "kind": "Gdef", "node": {".class": "FuncDef", "arg_kinds": [0], "arg_names": ["req"], "flags": ["is_coroutine"], "fullname": "server.handler_get", "name": "handler_get", "type": null}}, "logging": {".class": "SymbolTableNode", "cross_ref": "logging", "kind": "Gdef"}, "parser": {".class": "SymbolTableNode", "kind": "Gdef", "node": {".class": "Var", "flags": [], "fullname": "server.parser", "name": "parser", "type": "argparse.ArgumentParser"}}, "run_server": {".class": "SymbolTableNode", "kind": "Gdef", "node": {".class": "FuncDef", "arg_kinds": [0, 1], "arg_names": ["backend", "loop"], "flags": [], "fullname": "server.run_server", "name": "run_server", "type": null}}, "uuid": {".class": "SymbolTableNode", "cross_ref": "uuid", "kind": "Gdef"}, "web": {".class": "SymbolTableNode", "cross_ref": "aiohttp.web", "kind": "Gdef"}}, "path": "/home/bew/archive/typed_project/(argaen)aiocache/tests/performance/server.py"}